ex3/crescente/contador_sincrono_crescente.v
module contador_sincrono_crescente(CK, CLR, Q);
    input wire CK;    
    input wire CLR;    
    output reg [3:0] Q;  

    always @(posedge CK or posedge CLR) begin
        if (CLR)
            Q <= 4'b0000;      
        else
            Q <= Q + 1;         
    end
endmodule

ex3/crescente/contador_sincrono_crescente_tb.v
`timescale 1ns/1ns
`include "contador_sincrono_crescente.v" 

module contador_sincrono_crescente_tb;
    reg CK, CLR;
    wire [3:0] Q;

    contador_sincrono_crescente uut (CK, CLR, Q);
 
    initial begin
        $dumpfile("contador_sincrono_crescente_tb.vcd"); 
        $dumpvars(0, contador_sincrono_crescente_tb); 

        CLR = 1; #15 
        CLR = 0; #200;
        CLR = 1; #10 
        CLR = 0; #100;

        $display("Teste completo");                
        $finish;
    end

    initial begin
        CK = 0;
        forever #10 CK = ~CK;  
    end

endmodule

ex3/crescente/contador_sincrono_crescente_tb.vcd
$date
	Fri Nov 08 03:01:07 2024
$end
$version
	Icarus Verilog
$end
$timescale
	1ns
$end
$scope module contador_sincrono_crescente_tb $end
$var wire 4 ! Q [3:0] $end
$var reg 1 " CK $end
$var reg 1 # CLR $end
$scope module uut $end
$var wire 1 " CK $end
$var wire 1 # CLR $end
$var reg 4 $ Q [3:0] $end
$upscope $end
$upscope $end
$enddefinitions $end
$comment Show the parameter values. $end
$dumpall
$end
#0
$dumpvars
b0 $
1#
0"
b0 !
$end
#10
1"
#15
0#
#20
0"
#30
b1 !
b1 $
1"
#40
0"
#50
b10 !
b10 $
1"
#60
0"
#70
b11 !
b11 $
1"
#80
0"
#90
b100 !
b100 $
1"
#100
0"
#110
b101 !
b101 $
1"
#120
0"
#130
b110 !
b110 $
1"
#140
0"
#150
b111 !
b111 $
1"
#160
0"
#170
b1000 !
b1000 $
1"
#180
0"
#190
b1001 !
b1001 $
1"
#200
0"
#210
b1010 !
b1010 $
1"
#215
b0 !
b0 $
1#
#220
0"
#225
0#
#230
b1 !
b1 $
1"
#240
0"
#250
b10 !
b10 $
1"
#260
0"
#270
b11 !
b11 $
1"
#280
0"
#290
b100 !
b100 $
1"
#300
0"
#310
b101 !
b101 $
1"
