ex2/borda_subida.v
module borda_subida(J,K,CK,PR,CLR,Q);

    input J, K, CK, PR, CLR;
    output reg Q;

    always @(posedge CK) begin
        if (PR == 1'b1 && CLR == 1'b0)
            Q = 1'b0;
        else if (PR == 1'b0 && CLR == 1'b1)
            Q = 1'b1;
        else if (PR == 1'b0 && CLR == 1'b0)
            Q = 1'bx;
        else begin
            case({J, K})//PARA CONCATENAR
                2'b00: Q = Q;
                2'b01: Q = 1'b0;
                2'b10: Q = 1'b1;
                2'b11: Q = ~Q;
            endcase
        end
    end
endmodule

ex2/contador_assincrono_4bits.v
`include "borda_subida.v"  

module contador_assincrono_4bits(CK, PR, CLR, Q);
    input CK;              
    input PR, CLR;          
    output [3:0] Q;         

    borda_subida ff1(1'b1, 1'b1, CK,   PR, CLR, Q[0]);
    borda_subida ff2(1'b1, 1'b1, Q[0], PR, CLR, Q[1]);
    borda_subida ff3(1'b1, 1'b1, Q[1], PR, CLR, Q[2]);
    borda_subida ff4(1'b1, 1'b1, Q[2], PR, CLR, Q[3]);

endmodule

ex2/contador_assincrono_4bits_tb.v
`timescale 1ns/1ns
`include "contador_assincrono_4bits.v" 
module contador_assincrono_4bits_tb;

    reg CLK;         
    reg PR, CLR;     
    wire [3:0] Q;    
   
   contador_assincrono_4bits uut (CLK, PR, CLR, Q);

    initial begin
        $dumpfile("contador_assincrono_4bits_tb.vcd"); 
        $dumpvars(0, contador_assincrono_4bits_tb);     

       PR = 1; CLR = 0; #30 
       CLR = 1; #100
       CLR = 0; #20 
       CLR = 1; #100
                        
        $finish;            
        $display("Teste completo");
    end

    initial begin
        CLK = 0;
        forever #10 CLK = ~CLK; 
    end

endmodule

ex2/contador_assincrono_4bits_tb.vcd
$date
	Sat Nov 02 14:06:24 2024
$end
$version
	Icarus Verilog
$end
$timescale
	1ns
$end
$scope module contador_assincrono_4bits_tb $end
$var wire 4 ! Q [3:0] $end
$var reg 1 " CLK $end
$var reg 1 # CLR $end
$var reg 1 $ PR $end
$scope module uut $end
$var wire 1 " CK $end
$var wire 1 # CLR $end
$var wire 1 $ PR $end
$var wire 4 % Q [3:0] $end
$scope module ff1 $end
$var wire 1 " CK $end
$var wire 1 # CLR $end
$var wire 1 & J $end
$var wire 1 ' K $end
$var wire 1 $ PR $end
$var reg 1 ( Q $end
$upscope $end
$scope module ff2 $end
$var wire 1 ) CK $end
$var wire 1 # CLR $end
$var wire 1 * J $end
$var wire 1 + K $end
$var wire 1 $ PR $end
$var reg 1 , Q $end
$upscope $end
$scope module ff3 $end
$var wire 1 - CK $end
$var wire 1 # CLR $end
$var wire 1 . J $end
$var wire 1 / K $end
$var wire 1 $ PR $end
$var reg 1 0 Q $end
$upscope $end
$scope module ff4 $end
$var wire 1 1 CK $end
$var wire 1 # CLR $end
$var wire 1 2 J $end
$var wire 1 3 K $end
$var wire 1 $ PR $end
$var reg 1 4 Q $end
$upscope $end
$upscope $end
$upscope $end
$enddefinitions $end
$comment Show the parameter values. $end
$dumpall
$end
#0
$dumpvars
x4
13
12
x1
x0
1/
1.
x-
x,
1+
1*
x)
x(
1'
1&
bx %
1$
0#
0"
bx !
$end
#10
0)
bx0 !
bx0 %
0(
1"
#20
0"
#30
1)
bx1 !
bx1 %
1(
1"
1#
#40
0"
#50
0)
bx0 !
bx0 %
0(
1"
#60
0"
#70
1)
bx1 !
bx1 %
1(
1"
#80
0"
#90
0)
bx0 !
bx0 %
0(
1"
#100
0"
#110
1)
bx1 !
bx1 %
1(
1"
#120
0"
#130
0)
bx0 !
bx0 %
0(
1"
0#
#140
0"
#150
1)
bx1 !
bx1 %
1(
1"
1#
#160
0"
#170
0)
bx0 !
bx0 %
0(
1"
#180
0"
#190
1)
bx1 !
bx1 %
1(
1"
#200
0"
#210
0)
bx0 !
bx0 %
0(
1"
#220
0"
#230
1)
bx1 !
bx1 %
1(
1"
#240
0"
#250
0)
bx0 !
bx0 %
0(
1"
