ex3/decrescente/contador_sincrono_decrescente.v
module contador_sincrono_decrescente(CK, CLR, Q);
    input wire CK;      // Clock
    input wire CLR;   // Reset assíncrono
    output reg [5:0] Q;  // Saída de 6 bits para contagem de 35 a 10


    always @(negedge CK or posedge CLR) begin
        if (CLR)
            Q <= 6'd35;      // Define o contador no valor inicial 35
        else if (Q > 6'd10)
            Q <= Q - 1;      // Decrementa o contador
        else
            Q <= 6'd35;      // Reinicia para 35 quando atingir 10
    end
endmodule

ex3/decrescente/contador_sincrono_decrescente_tb.v
`timescale 1ns/1ns
`include "contador_sincrono_decrescente.v" 

module contador_sincrono_decrescente_tb;
    reg CK, CLR;
    wire [5:0] Q;

    // Instancia o contador
    contador_sincrono_decrescente uut (CK, CLR, Q);

    // Sinais de reset e teste
    initial begin
        $dumpfile("contador_sincrono_decrescente_tb.vcd"); 
        $dumpvars(0, contador_sincrono_decrescente_tb); 

        CLR = 1;
        #15 CLR = 0;            // Libera o reset após 15 unidades de tempo

        // Testa a contagem por um tempo
        #400;
        CLR = 1;                // Aplica reset novamente
        #10 CLR = 0;

        #100;
        $display("Teste completo");                
        $finish;             
               
    end

    // Geração de clock
    initial begin
        CK = 0;
        forever #10 CK = ~CK;  // Clock com período de 20 unidades de tempo
    end
endmodule

ex3/decrescente/contador_sincrono_decrescente_tb.vcd
$date
	Fri Nov 08 03:12:09 2024
$end
$version
	Icarus Verilog
$end
$timescale
	1ns
$end
$scope module contador_sincrono_decrescente_tb $end
$var wire 6 ! Q [5:0] $end
$var reg 1 " CK $end
$var reg 1 # CLR $end
$scope module uut $end
$var wire 1 " CK $end
$var wire 1 # CLR $end
$var reg 6 $ Q [5:0] $end
$upscope $end
$upscope $end
$enddefinitions $end
$comment Show the parameter values. $end
$dumpall
$end
#0
$dumpvars
b100011 $
1#
0"
b100011 !
$end
#10
1"
#15
0#
#20
b100010 !
b100010 $
0"
#30
1"
#40
b100001 !
b100001 $
0"
#50
1"
#60
b100000 !
b100000 $
0"
#70
1"
#80
b11111 !
b11111 $
0"
#90
1"
#100
b11110 !
b11110 $
0"
#110
1"
#120
b11101 !
b11101 $
0"
#130
1"
#140
b11100 !
b11100 $
0"
#150
1"
#160
b11011 !
b11011 $
0"
#170
1"
#180
b11010 !
b11010 $
0"
#190
1"
#200
b11001 !
b11001 $
0"
#210
1"
#220
b11000 !
b11000 $
0"
#230
1"
#240
b10111 !
b10111 $
0"
#250
1"
#260
b10110 !
b10110 $
0"
#270
1"
#280
b10101 !
b10101 $
0"
#290
1"
#300
b10100 !
b10100 $
0"
#310
1"
#320
b10011 !
b10011 $
0"
#330
1"
#340
b10010 !
b10010 $
0"
#350
1"
#360
b10001 !
b10001 $
0"
#370
1"
#380
b10000 !
b10000 $
0"
#390
1"
#400
b1111 !
b1111 $
0"
#410
1"
#415
b100011 !
b100011 $
1#
#420
0"
#425
0#
#430
1"
#440
b100010 !
b100010 $
0"
#450
1"
#460
b100001 !
b100001 $
0"
#470
1"
#480
b100000 !
b100000 $
0"
#490
1"
#500
b11111 !
b11111 $
0"
#510
1"
#520
b11110 !
b11110 $
0"
